README.rst
setup.py
pyramid_admin2_cqlengine/__init__.py
pyramid_admin2_cqlengine.egg-info/PKG-INFO
pyramid_admin2_cqlengine.egg-info/SOURCES.txt
pyramid_admin2_cqlengine.egg-info/dependency_links.txt
pyramid_admin2_cqlengine.egg-info/not-zip-safe
pyramid_admin2_cqlengine.egg-info/requires.txt
pyramid_admin2_cqlengine.egg-info/top_level.txt